tabletest3/__init__.py
tabletest3-1.1.0.dist-info/DESCRIPTION.rst
tabletest3-1.1.0.dist-info/METADATA
tabletest3-1.1.0.dist-info/metadata.json
tabletest3-1.1.0.dist-info/RECORD
tabletest3-1.1.0.dist-info/top_level.txt
tabletest3-1.1.0.dist-info/WHEEL
